spalette/__init__.py
spalette/__main__.py
spalette/color_module.py
spalette-0.1.dist-info/LICENSE
spalette-0.1.dist-info/METADATA
spalette-0.1.dist-info/WHEEL
spalette-0.1.dist-info/entry_points.txt
spalette-0.1.dist-info/RECORD
