Metadata-Version: 2.1
Name: spalette
Version: 0.1
Summary: a simple color palette generator that takes an image file as input
License: MIT
Author: grrhale
Author-email: raymond.hale0@gmail.com
Requires-Python: >=3.7,<4.0
Classifier: License :: OSI Approved :: MIT License
Classifier: Programming Language :: Python :: 3
Classifier: Programming Language :: Python :: 3.7
Classifier: Programming Language :: Python :: 3.8
Classifier: Programming Language :: Python :: 3.9
Classifier: Programming Language :: Python :: 3.10
Classifier: Programming Language :: Python :: 3.11
Requires-Dist: matplotlib (>=3.7.2,<4.0.0)
Requires-Dist: opencv-python (>=4.8.0.76,<5.0.0.0)
